locopilot/__init__.py
locopilot/cli/__init__.py
locopilot/cli/app.py
locopilot/core/__init__.py
locopilot/core/agent.py
locopilot/core/executor.py
locopilot/core/memory.py
locopilot/llm/__init__.py
locopilot/llm/connection.py
locopilot/utils/__init__.py
locopilot/utils/file_ops.py
locopilot-0.1.10.dist-info/licenses/LICENSE
locopilot-0.1.10.dist-info/METADATA
locopilot-0.1.10.dist-info/WHEEL
locopilot-0.1.10.dist-info/entry_points.txt
locopilot-0.1.10.dist-info/top_level.txt
locopilot-0.1.10.dist-info/RECORD
