Metadata-Version: 2.4
Name: locopilot
Version: 0.1.10
Summary: An open-source, local-first, agentic coding assistant
Author-email: Ripan Roy <ripanroy111@gmail.com>
License: MIT
Project-URL: Homepage, https://github.com/Ripan-Roy/locopilot-ai
Project-URL: Repository, https://github.com/Ripan-Roy/locopilot-ai.git
Project-URL: Issues, https://github.com/Ripan-Roy/locopilot-ai/issues
Keywords: coding-assistant,llm,langchain,langgraph,local-ai
Classifier: Development Status :: 3 - Alpha
Classifier: Intended Audience :: Developers
Classifier: License :: OSI Approved :: MIT License
Classifier: Programming Language :: Python :: 3
Classifier: Programming Language :: Python :: 3.8
Classifier: Programming Language :: Python :: 3.9
Classifier: Programming Language :: Python :: 3.10
Classifier: Programming Language :: Python :: 3.11
Classifier: Topic :: Software Development :: Code Generators
Classifier: Topic :: Software Development :: Libraries :: Python Modules
Requires-Python: >=3.8
License-File: LICENSE
Requires-Dist: typer[all]>=0.9.0
Requires-Dist: langchain>=0.1.0
Requires-Dist: langgraph>=0.0.20
Requires-Dist: langchain-community>=0.0.10
Requires-Dist: langchain-ollama>=0.3.0
Requires-Dist: pyyaml>=6.0
Requires-Dist: httpx>=0.24.0
Requires-Dist: rich>=13.0.0
Requires-Dist: prompt-toolkit>=3.0.0
Requires-Dist: pydantic>=2.0.0
Requires-Dist: python-dotenv>=1.0.0
Provides-Extra: dev
Requires-Dist: pytest>=7.0.0; extra == "dev"
Requires-Dist: pytest-cov>=4.0.0; extra == "dev"
Requires-Dist: pytest-asyncio>=0.21.0; extra == "dev"
Requires-Dist: black>=23.0.0; extra == "dev"
Requires-Dist: isort>=5.12.0; extra == "dev"
Requires-Dist: flake8>=6.0.0; extra == "dev"
Requires-Dist: mypy>=1.0.0; extra == "dev"
Dynamic: license-file
